WeReadScan/WeRead.py
WeReadScan/__init__.py
WeReadScan/script/__init__.py
WeReadScan/script/os_util.py
WeReadScan_HTML-0.1.1.dist-info/METADATA
WeReadScan_HTML-0.1.1.dist-info/WHEEL
WeReadScan_HTML-0.1.1.dist-info/top_level.txt
WeReadScan_HTML-0.1.1.dist-info/RECORD
