Metadata-Version: 2.1
Name: WeReadScan-HTML
Version: 0.1.1
Summary: WeRead HTML Scanner
Home-page: https://github.com/Algebra-FUN/WeReadScan/tree/html-variant
Author: Algebra-FUN
Author-email: algebra-fun@outlook.com
License: GPL Licence
Keywords: weread,scan,pdf,convert,selenium
Platform: windows
Platform: macos
Platform: linux
Requires-Python: >=3.6
Requires-Dist: selenium
Requires-Dist: numpy
Requires-Dist: matplotlib
